zuulfmt/__init__.py
zuulfmt/__main__.py
zuulfmt-0.2.0.dist-info/LICENSE
zuulfmt-0.2.0.dist-info/METADATA
zuulfmt-0.2.0.dist-info/WHEEL
zuulfmt-0.2.0.dist-info/entry_points.txt
zuulfmt-0.2.0.dist-info/top_level.txt
zuulfmt-0.2.0.dist-info/RECORD
